vsml/__init__.py
vsml-0.1.dist-info/LICENSE.txt
vsml-0.1.dist-info/METADATA
vsml-0.1.dist-info/WHEEL
vsml-0.1.dist-info/top_level.txt
vsml-0.1.dist-info/RECORD
